{
    "id": "427993",
    "teams": [
        {
            "name": "NRG Esports",
            "score": "0",
            "country": "us",
            "won": false
        },
        {
            "name": "Cloud9",
            "score": "2",
            "country": "us",
            "won": true
        }
    ],
    "status": "Completed",
    "ago": "1w 3d",
    "event": "Main Event\u2013Upper Round 1",
    "tournament": "Champions Tour 2025: Americas Kickoff",
    "img": "https://owcdn.net/img/640f5ab71dfbb.png"
}